azureloggerbundle/AzureLoggerBundle.py
azureloggerbundle/AzureLoggerBundleTest.py
azureloggerbundle/_config/config.yaml
azureloggerbundle/_config/config_test.yaml
azureloggerbundle/app_insights/AppInsightsLogHandlerFactory.py
azureloggerbundle/app_insights/AzureLogWithExtraHandler.py
azure_logger_bundle-0.3.1.dist-info/entry_points.txt
azure_logger_bundle-0.3.1.dist-info/LICENSE
azure_logger_bundle-0.3.1.dist-info/WHEEL
azure_logger_bundle-0.3.1.dist-info/METADATA
azure_logger_bundle-0.3.1.dist-info/RECORD
